easyGPGTool/__init__.py
easyGPGTool/_aboutUs_.py
easyGPGTool/_decrypt_.py
easyGPGTool/_encrypt_.py
easyGPGTool/_export_.py
easyGPGTool/_extensions_.py
easyGPGTool/_import_.py
easyGPGTool/_newkey_.py
easyGPGTool/_patchNote_.py
easyGPGTool/_removeKey_.py
easyGPGTool/_trust_.py
easyGPGTool/core.py
easyGPGTool/patch_notes/0.1_patch_note.log
easyGPGTool/patch_notes/beta_patch_note.log
easyGPGTool/pictures/aboutUs.png
easyGPGTool/pictures/decrypt.png
easyGPGTool/pictures/encrypt.png
easyGPGTool/pictures/export.png
easyGPGTool/pictures/gpgIcon.ico
easyGPGTool/pictures/import.png
easyGPGTool/pictures/informationIcon.ico
easyGPGTool/pictures/newIcon.png
easyGPGTool/pictures/patchNote.png
easyGPGTool/pictures/quit.png
easyGPGTool/pictures/removeIcon.png
easyGPGTool/pictures/trust.png
easyGPGTool-0.1.dist-info/LICENSE
easyGPGTool-0.1.dist-info/METADATA
easyGPGTool-0.1.dist-info/WHEEL
easyGPGTool-0.1.dist-info/top_level.txt
easyGPGTool-0.1.dist-info/RECORD
