Metadata-Version: 2.1
Name: easyGPGTool
Version: 0.1
Summary: A GUI GPG tool application
Home-page: https://github.com/MehdiREXON/easyGPGTool
Author: Mehdi Ghazanfari
Author-email: mehdirexon@gmail.com
License: MIT
Classifier: License :: OSI Approved :: MIT License
Classifier: Programming Language :: Python :: 3.1
Classifier: Operating System :: POSIX :: Linux
Classifier: Topic :: Security :: Cryptography
Requires-Python: >=3.10
License-File: LICENSE
Requires-Dist: plyer
Requires-Dist: colorama
Requires-Dist: python-gnupg
Requires-Dist: python-magic
Requires-Dist: python-dateutil
Requires-Dist: PySide6
